joke/__init__.py
joke/cli.py
joke/joke.py
joke/spinner.py
joke_api-1.0.0.dist-info/LICENSE
joke_api-1.0.0.dist-info/METADATA
joke_api-1.0.0.dist-info/WHEEL
joke_api-1.0.0.dist-info/entry_points.txt
joke_api-1.0.0.dist-info/top_level.txt
joke_api-1.0.0.dist-info/RECORD
