Metadata-Version: 2.1
Name: joke-api
Version: 1.0.0
Summary: A cool wrapper for Joke API
Home-page: UNKNOWN
Author: proguy914629
License: UNKNOWN
Keywords: joke,jokes,wrapper,api
Platform: UNKNOWN
Classifier: Development Status :: 5 - Production/Stable
Classifier: Natural Language :: English
Classifier: Programming Language :: Python :: 3
Classifier: License :: OSI Approved :: MIT License
Requires-Python: >=3.5
Requires-Dist: requests
